Workbook

Sheet Customers
A1: customer_id | B1: customer_name | C1: city | D1: segment | E1: signup_channel | F1: signup_date | G1: email | H1: phone | I1: has_email | J1: has_phone
A2: C0001 | B2: Allison Hill | C2: Hyderabad | D2: New | E2: Organic | F2: 45423 | G2: allison.hill@example.com | H2: 001-218-519-6001x3389 | I2: TRUE | J2: TRUE
A3: C0002 | B3: Meredith Barnes | C3: Hyderabad | D3: Returning | E3: Paid Ads | F3: 45664 | G3: meredith.barnes@example.com | H3: 302-765-4235x116 | I3: TRUE | J3: TRUE
A4: C0003 | B4: Lindsey Roman | C4: Delhi | D4: New | E4: Organic | F4: 45963 | G4: lindsey.roman@example.com | H4: +1-516-318-4959 | I4: TRUE | J4: TRUE
A5: C0004 | B5: Darren Roberts | C5: Hyderabad | D5: VIP | E5: Email | F5: 45270 | G5: darren.roberts@example.com | I5: TRUE | J5: FALSE
A6: C0005 | B6: BRIAN RAMIREZ | C6: Chandigarh | D6: VIP | E6: Social Media | F6: 45863 | G6: brian.ramirez@example.com | H6: (925)853-4192x832 | I6: TRUE | J6: TRUE
A7: C0006 | B7: Timothy Watts | C7: Chandigarh | D7: New | E7: Organic | F7: 45419 | H7: 903-405-6413x95376 | I7: FALSE | J7: TRUE
A8: C0007 | B8: David Hoffman | C8: Delhi | D8: New | E8: Email | F8: 45465 | G8: david.hoffman@example.com | H8: 001-369-265-3287 | I8: TRUE | J8: TRUE
A9: C0008 | B9: Brittany Moore | C9: Pune | D9: New | E9: Email | F9: 45910 | G9: brittany.moore@example.com | I9: TRUE | J9: FALSE
A10: C0009 | B10: Janice Carlson | C10: Delhi | D10: VIP | E10: Email | F10: 45684 | G10: janice.carlson@example.com | H10: 280-618-4514x627 | I10: TRUE | J10: TRUE
A11: C0010 | B11: PAMELA ROMERO | C11: Bangalore | D11: New | E11: Social Media | F11: 45299 | G11: pamela.romero@example.com | H11: +1-948-293-2528x8095 | I11: TRUE | J11: TRUE
A12: C0011 | B12: Jack Galloway | C12: Pune | D12: Returning | E12: Organic | F12: 46045 | G12: jack.galloway@example.com | H12: 403.491.1718 | I12: TRUE | J12: TRUE
A13: C0012 | B13: Theresa Martin | C13: Delhi | D13: VIP | E13: Social Media | F13: 45747 | I13: FALSE | J13: FALSE
A14: C0013 | B14: Tracey Hickman | C14: Mumbai | D14: Returning | E14: Paid Ads | F14: 45990 | G14: tracey.hickman@example.com | H14: 001-734-265-7871x331 | I14: TRUE | J14: TRUE
A15: C0014 | B15: Crystal Robinson | C15: Delhi | D15: Returning | E15: Organic | F15: 45261 | G15: crystal.robinson@example.com | H15: +1-403-910-5183x4738 | I15: TRUE | J15: TRUE
A16: C0015 | B16: JOHN RUSSELL | C16: Chandigarh | D16: Returning | E16: Organic | F16: 45286 | G16: john.russell@example.com | H16: +1-565-966-7010x65133 | I16: TRUE | J16: TRUE
A17: C0016 | B17: Clifford Ford | C17: Mumbai | D17: Returning | E17: Email | F17: 46117 | G17: clifford.ford@example.com | I17: TRUE | J17: FALSE
A18: C0017 | B18: Robert Chase | C18: Mumbai | D18: New | E18: Social Media | F18: 45290 | G18: robert.chase@example.com | H18: +1-880-213-2677x3602 | I18: TRUE | J18: TRUE
A19: C0018 | B19: Mrs. Rachel Gibson | C19: Pune | D19: New | E19: Social Media | F19: 45636 | H19: 001-287-923-4309x8050 | I19: FALSE | J19: TRUE
A20: C0019 | B20: Sarah Moore | C20: Chandigarh | D20: VIP | E20: Referral | F20: 46209 | G20: sarah.moore@example.com | H20: 521-291-3619 | I20: TRUE | J20: TRUE
A21: C0020 | B21: JENNIFER SILVA | C21: Hyderabad | D21: VIP | E21: Referral | F21: 45742 | G21: jennifer.silva@example.com | I21: TRUE | J21: FALSE
A22: C0021 | B22: Christina Moran | C22: Pune | D22: New | E22: Organic | F22: 45440 | G22: christina.moran@example.com | H22: (524)675-1079x9118 | I22: TRUE | J22: TRUE
A23: C0022 | B23: Gregory Jones | C23: Chandigarh | D23: VIP | E23: Paid Ads | F23: 45446 | G23: gregory.jones@example.com | H23: 327-384-9808x4124 | I23: TRUE | J23: TRUE
A24: C0023 | B24: Brittney Campbell | C24: Mumbai | D24: New | E24: Paid Ads | F24: 45410 | G24: brittney.campbell@example.com | H24: 634-487-4016x40052 | I24: TRUE | J24: TRUE
A25: C0024 | B25: Kristen Patterson | C25: Chandigarh | D25: Returning | E25: Referral | F25: 45196 | I25: FALSE | J25: FALSE
A26: C0025 | B26: STEPHEN MCKEE | C26: Bangalore | D26: VIP | E26: Referral | F26: 45767 | G26: stephen.mckee@example.com | H26: (598)326-2045x053 | I26: TRUE | J26: TRUE
A27: C0026 | B27: Justin Baxter | C27: Delhi | D27: Returning | E27: Referral | F27: 46223 | G27: justin.baxter@example.com | H27: 001-323-822-6025x6342 | I27: TRUE | J27: TRUE
A28: C0027 | B28: Shannon Walker | C28: Delhi | D28: VIP | E28: Referral | F28: 46055 | G28: shannon.walker@example.com | H28: 754.833.0365x414 | I28: TRUE | J28: TRUE
A29: C0028 | B29: Sarah Rivera | C29: Hyderabad | D29: VIP | E29: Organic | F29: 45215 | G29: sarah.rivera@example.com | I29: TRUE | J29: FALSE
A30: C0029 | B30: Debbie Carpenter | C30: Pune | D30: VIP | E30: Paid Ads | F30: 46233 | G30: debbie.carpenter@example.com | H30: 3198655698 | I30: TRUE | J30: TRUE
A31: C0030 | B31: CHERYL WILLIAMS | C31: Pune | D31: VIP | E31: Paid Ads | F31: 45650 | H31: 783.856.1595x14846 | I31: FALSE | J31: TRUE
A32: C0031 | B32: Kristen Lee | C32: Delhi | D32: Returning | E32: Social Media | F32: 45894 | G32: kristen.lee@example.com | H32: (729)994-6804x4369 | I32: TRUE | J32: TRUE
A33: C0032 | B33: Michael Dixon | C33: Mumbai | D33: VIP | E33: Email | F33: 46031 | G33: michael.dixon@example.com | I33: TRUE | J33: FALSE
A34: C0033 | B34: Nancy Hopkins | C34: Delhi | D34: VIP | E34: Referral | F34: 45488 | G34: nancy.hopkins@example.com | H34: +1-395-913-4332x00379 | I34: TRUE | J34: TRUE
A35: C0034 | B35: Mark Lee | C35: Chandigarh | D35: New | E35: Organic | F35: 45927 | G35: mark.lee@example.com | H35: 563.320.1632x8708 | I35: TRUE | J35: TRUE
A36: C0035 | B36: ROBERT CONTRERAS | C36: Mumbai | D36: Returning | E36: Referral | F36: 46238 | G36: robert.contreras@example.com | H36: +1-557-698-6872x774 | I36: TRUE | J36: TRUE
A37: C0036 | B37: Kelly Sims | C37: Chandigarh | D37: New | E37: Email | F37: 45478 | I37: FALSE | J37: FALSE
A38: C0037 | B38: Dustin Nelson | C38: Hyderabad | D38: Returning | E38: Paid Ads | F38: 45526 | G38: dustin.nelson@example.com | H38: +1-812-823-6231 | I38: TRUE | J38: TRUE
A39: C0038 | B39: John Brown | C39: Hyderabad | D39: Returning | E39: Social Media | F39: 46073 | G39: john.brown@example.com | H39: (590)996-7054x6688 | I39: TRUE | J39: TRUE
A40: C0039 | B40: Jeffrey Johnson | C40: Hyderabad | D40: Returning | E40: Paid Ads | F40: 45543 | G40: jeffrey.johnson@example.com | H40: +1-462-972-9806x99016 | I40: TRUE | J40: TRUE
A41: C0040 | B41: DAVID MURPHY | C41: Mumbai | D41: New | E41: Paid Ads | F41: 45670 | G41: david.murphy@example.com | I41: TRUE | J41: FALSE
A42: C0041 | B42: Shawn Ramirez | C42: Hyderabad | D42: VIP | E42: Email | F42: 46199 | G42: shawn.ramirez@example.com | H42: (241)470-8053x10033 | I42: TRUE | J42: TRUE
A43: C0042 | B43: John Wilson | C43: Mumbai | D43: VIP | E43: Email | F43: 46195 | H43: 645.829.9124x190 | I43: FALSE | J43: TRUE
A44: C0043 | B44: Miguel Jones | C44: Bangalore | D44: VIP | E44: Social Media | F44: 45921 | G44: miguel.jones@example.com | H44: +1-731-249-1905x8651 | I44: TRUE | J44: TRUE
A45: C0044 | B45: Samantha Garcia | C45: Mumbai | D45: New | E45: Paid Ads | F45: 46209 | G45: samantha.garcia@example.com | I45: TRUE | J45: FALSE
A46: C0045 | B46: SANDRA ZIMMERMAN | C46: Pune | D46: Returning | E46: Organic | F46: 45649 | G46: sandra.zimmerman@example.com | H46: 001-684-998-7769x4531 | I46: TRUE | J46: TRUE
A47: C0046 | B47: John Bishop | C47: Chandigarh | D47: New | E47: Paid Ads | F47: 45589 | G47: john.bishop@example.com | H47: 6756273545 | I47: TRUE | J47: TRUE
A48: C0047 | B48: Kellie Lee | C48: Hyderabad | D48: New | E48: Social Media | F48: 45443 | G48: kellie.lee@example.com | H48: (778)937-7701x43634 | I48: TRUE | J48: TRUE
A49: C0048 | B49: Hailey Barajas | C49: Pune | D49: New | E49: Social Media | F49: 45772 | I49: FALSE | J49: FALSE
A50: C0049 | B50: Jesse Parker | C50: Bangalore | D50: VIP | E50: Social Media | F50: 45431 | G50: jesse.parker@example.com | H50: 001-635-318-2337x4989 | I50: TRUE | J50: TRUE
A51: C0050 | B51: ELIZABETH WARD | C51: Pune | D51: Returning | E51: Email | F51: 45507 | G51: elizabeth.ward@example.com | H51: 001-682-940-0842x710 | I51: TRUE | J51: TRUE
A52: C0051 | B52: Glen Sheppard | C52: Chandigarh | D52: VIP | E52: Organic | F52: 45454 | G52: glen.sheppard@example.com | H52: 511.367.1902x2941 | I52: TRUE | J52: TRUE
A53: C0052 | B53: Jennifer Carlson | C53: Hyderabad | D53: VIP | E53: Referral | F53: 45844 | G53: jennifer.carlson@example.com | I53: TRUE | J53: FALSE
A54: C0053 | B54: Jamie Kerr | C54: Hyderabad | D54: Returning | E54: Organic | F54: 45502 | G54: jamie.kerr@example.com | H54: 001-564-699-0913 | I54: TRUE | J54: TRUE
A55: C0054 | B55: Brooke Thompson | C55: Mumbai | D55: Returning | E55: Paid Ads | F55: 45265 | H55: 6679974034 | I55: FALSE | J55: TRUE
A56: C0055 | B56: DAVID BAKER | C56: Bangalore | D56: New | E56: Referral | F56: 46028 | G56: david.baker@example.com | H56: 001-336-218-3242 | I56: TRUE | J56: TRUE
A57: C0056 | B57: Eric Curry | C57: Pune | D57: New | E57: Email | F57: 45792 | G57: eric.curry@example.com | I57: TRUE | J57: FALSE
A58: C0057 | B58: Caleb Barker | C58: Chandigarh | D58: VIP | E58: Referral | F58: 45931 | G58: caleb.barker@example.com | H58: 288-377-1906x594 | I58: TRUE | J58: TRUE
A59: C0058 | B59: Michael Valencia | C59: Hyderabad | D59: VIP | E59: Email | F59: 45811 | G59: michael.valencia@example.com | H59: 4498027874 | I59: TRUE | J59: TRUE
A60: C0059 | B60: Katherine Davis | C60: Delhi | D60: New | E60: Referral | F60: 45556 | G60: katherine.davis@example.com | H60: 651-725-6746x80715 | I60: TRUE | J60: TRUE
A61: C0060 | B61: RAYMOND HANCOCK | C61: Delhi | D61: VIP | E61: Email | F61: 46064 | I61: FALSE | J61: FALSE
A62: C0061 | B62: Sean Murray | C62: Chandigarh | D62: VIP | E62: Referral | F62: 45243 | G62: sean.murray@example.com | H62: 259.577.0348x24771 | I62: TRUE | J62: TRUE
A63: C0062 | B63: Emily Smith | C63: Bangalore | D63: New | E63: Organic | F63: 45620 | G63: emily.smith@example.com | H63: 817.912.7484 | I63: TRUE | J63: TRUE
A64: C0063 | B64: Mrs. Kristen Reyes | C64: Mumbai | D64: Returning | E64: Paid Ads | F64: 46167 | G64: mrs..kristen.reyes@example.com | H64: 421.946.5840x44997 | I64: TRUE | J64: TRUE
A65: C0064 | B65: Haley Arnold | C65: Chandigarh | D65: New | E65: Email | F65: 45764 | G65: haley.arnold@example.com | I65: TRUE | J65: FALSE
A66: C0065 | B66: FRANK LOPEZ | C66: Chandigarh | D66: New | E66: Social Media | F66: 45928 | G66: frank.lopez@example.com | H66: 001-463-960-5766 | I66: TRUE | J66: TRUE
A67: C0066 | B67: Beth Sanford | C67: Chandigarh | D67: VIP | E67: Paid Ads | F67: 45539 | H67: 371-987-0262 | I67: FALSE | J67: TRUE
A68: C0067 | B68: Deborah Hanson | C68: Delhi | D68: VIP | E68: Social Media | F68: 45609 | G68: deborah.hanson@example.com | H68: 358-565-7809 | I68: TRUE | J68: TRUE
A69: C0068 | B69: Tammie Bright | C69: Pune | D69: New | E69: Referral | F69: 45981 | G69: tammie.bright@example.com | I69: TRUE | J69: FALSE
A70: C0069 | B70: Brett Schultz | C70: Pune | D70: VIP | E70: Social Media | F70: 46115 | G70: brett.schultz@example.com | H70: 524.800.5045x562 | I70: TRUE | J70: TRUE
A71: C0070 | B71: REBECCA JACKSON | C71: Delhi | D71: VIP | E71: Paid Ads | F71: 45270 | G71: rebecca.jackson@example.com | H71: (693)479-2374x7407 | I71: TRUE | J71: TRUE
A72: C0071 | B72: Tony Huerta | C72: Hyderabad | D72: Returning | E72: Social Media | F72: 45504 | G72: tony.huerta@example.com | H72: (647)243-6713x69594 | I72: TRUE | J72: TRUE
A73: C0072 | B73: Mary Hill | C73: Hyderabad | D73: VIP | E73: Referral | F73: 45788 | I73: FALSE | J73: FALSE
A74: C0073 | B74: Natasha Williams | C74: Bangalore | D74: VIP | E74: Social Media | F74: 45831 | G74: natasha.williams@example.com | H74: 943.295.3394x2104 | I74: TRUE | J74: TRUE
A75: C0074 | B75: Morgan Davis | C75: Chandigarh | D75: New | E75: Paid Ads | F75: 45500 | G75: morgan.davis@example.com | H75: 001-662-732-8588x4247 | I75: TRUE | J75: TRUE
A76: C0075 | B76: JULIE JONES | C76: Chandigarh | D76: Returning | E76: Organic | F76: 45989 | G76: julie.jones@example.com | H76: 368.951.6048 | I76: TRUE | J76: TRUE
A77: C0076 | B77: Paul Baker | C77: Pune | D77: VIP | E77: Paid Ads | F77: 45591 | G77: paul.baker@example.com | I77: TRUE | J77: FALSE
A78: C0077 | B78: Jacqueline Leonard | C78: Pune | D78: New | E78: Organic | F78: 45688 | G78: jacqueline.leonard@example.com | H78: +1-285-693-1746x120 | I78: TRUE | J78: TRUE
A79: C0078 | B79: Audrey Young DDS | C79: Chandigarh | D79: VIP | E79: Organic | F79: 45599 | H79: (786)592-6179x640 | I79: FALSE | J79: TRUE
A80: C0079 | B80: Trevor Foley | C80: Delhi | D80: New | E80: Organic | F80: 45291 | G80: trevor.foley@example.com | H80: +1-258-750-6431x71390 | I80: TRUE | J80: TRUE
A81: C0080 | B81: CAMERON CUNNINGHAM | C81: Mumbai | D81: New | E81: Email | F81: 45259 | G81: cameron.cunningham@example.com | I81: TRUE | J81: FALSE
A82: C0081 | B82: Christine Robinson | C82: Delhi | D82: Returning | E82: Social Media | F82: 46112 | G82: christine.robinson@example.com | H82: 729-504-2284x21020 | I82: TRUE | J82: TRUE
A83: C0082 | B83: Alexis Baker | C83: Delhi | D83: VIP | E83: Paid Ads | F83: 45320 | G83: alexis.baker@example.com | H83: (281)617-7589x17839 | I83: TRUE | J83: TRUE
A84: C0083 | B84: Victor Brown | C84: Hyderabad | D84: VIP | E84: Email | F84: 45696 | G84: victor.brown@example.com | H84: (761)877-1159x2124 | I84: TRUE | J84: TRUE
A85: C0084 | B85: Kerry Chavez DDS | C85: Bangalore | D85: New | E85: Social Media | F85: 45291 | I85: FALSE | J85: FALSE
A86: C0085 | B86: SARAH CURTIS | C86: Bangalore | D86: New | E86: Organic | F86: 46004 | G86: sarah.curtis@example.com | H86: 001-736-673-6576x6156 | I86: TRUE | J86: TRUE
A87: C0086 | B87: Christian Leblanc | C87: Chandigarh | D87: VIP | E87: Social Media | F87: 45257 | G87: christian.leblanc@example.com | H87: 716-315-2809 | I87: TRUE | J87: TRUE
A88: C0087 | B88: Shane Pugh | C88: Mumbai | D88: Returning | E88: Social Media | F88: 45636 | G88: shane.pugh@example.com | H88: 001-304-794-5198x3273 | I88: TRUE | J88: TRUE
A89: C0088 | B89: Holly Farmer | C89: Bangalore | D89: VIP | E89: Organic | F89: 45797 | G89: holly.farmer@example.com | I89: TRUE | J89: FALSE
A90: C0089 | B90: Sarah Villegas | C90: Hyderabad | D90: VIP | E90: Organic | F90: 46057 | G90: sarah.villegas@example.com | H90: +1-480-494-0244x550 | I90: TRUE | J90: TRUE
A91: C0090 | B91: JENNIFER THOMAS | C91: Chandigarh | D91: Returning | E91: Referral | F91: 45860 | H91: 7186366752 | I91: FALSE | J91: TRUE
A92: C0091 | B92: Paula Bradley | C92: Chandigarh | D92: New | E92: Paid Ads | F92: 45276 | G92: paula.bradley@example.com | H92: 9229901476 | I92: TRUE | J92: TRUE
A93: C0092 | B93: Daniel Hunt | C93: Delhi | D93: VIP | E93: Social Media | F93: 45553 | G93: daniel.hunt@example.com | I93: TRUE | J93: FALSE
A94: C0093 | B94: Michael Watkins | C94: Delhi | D94: Returning | E94: Paid Ads | F94: 45747 | G94: michael.watkins@example.com | H94: 703-369-0034x3244 | I94: TRUE | J94: TRUE
A95: C0094 | B95: Paul Thompson | C95: Mumbai | D95: Returning | E95: Paid Ads | F95: 45590 | G95: paul.thompson@example.com | H95: 001-738-885-1606x071 | I95: TRUE | J95: TRUE
A96: C0095 | B96: MICHELLE BUTLER | C96: Chandigarh | D96: Returning | E96: Email | F96: 45308 | G96: michelle.butler@example.com | H96: 5528975161 | I96: TRUE | J96: TRUE
A97: C0096 | B97: Kelly Foster | C97: Chandigarh | D97: New | E97: Email | F97: 45516 | I97: FALSE | J97: FALSE
A98: C0097 | B98: Gary Jackson | C98: Chandigarh | D98: New | E98: Paid Ads | F98: 45729 | G98: gary.jackson@example.com | H98: 488-635-5231 | I98: TRUE | J98: TRUE
A99: C0098 | B99: Lance Wolf | C99: Delhi | D99: Returning | E99: Social Media | F99: 45884 | G99: lance.wolf@example.com | H99: (777)499-7995 | I99: TRUE | J99: TRUE
A100: C0099 | B100: John Welch | C100: Bangalore | D100: New | E100: Social Media | F100: 46034 | G100: john.welch@example.com | H100: 001-205-781-4770 | I100: TRUE | J100: TRUE
...

Sheet Order Items
A1: order_item_id | B1: order_id | C1: product_id | D1: quantity | E1: discount_pct | F1: quantity_was_imputed | G1: unit_price | H1: category | I1: line_total | J1: order_date | K1: customer_id
A2: OI000001 | B2: O00001 | C2: PR016 | D2: 4 | E2: 0 | F2: FALSE | G2: =VLOOKUP(C2,Products!A:D,4,FALSE) -> 1130 | H2: =VLOOKUP(C2,Products!A:D,3,FALSE) -> Books | I2: =G2*D2*(1-E2) -> 4520 | J2: =VLOOKUP(B2,Orders!A:C,3,FALSE) -> 46260 | K2: =VLOOKUP(B2,Orders!A:B,2,FALSE) -> C0247
A3: OI000002 | B3: O00002 | C3: PR075 | D3: 5 | E3: 0.1 | F3: FALSE | G3: =VLOOKUP(C3,Products!A:D,4,FALSE) -> 1475 | H3: =VLOOKUP(C3,Products!A:D,3,FALSE) -> Books | I3: =G3*D3*(1-E3) -> 6637.5 | J3: =VLOOKUP(B3,Orders!A:C,3,FALSE) -> 45812 | K3: =VLOOKUP(B3,Orders!A:B,2,FALSE) -> C0174
A4: OI000003 | B4: O00002 | C4: PR010 | D4: 4 | E4: 0 | F4: FALSE | G4: =VLOOKUP(C4,Products!A:D,4,FALSE) -> 2450 | H4: =VLOOKUP(C4,Products!A:D,3,FALSE) -> Sports | I4: =G4*D4*(1-E4) -> 9800 | J4: =VLOOKUP(B4,Orders!A:C,3,FALSE) -> 45812 | K4: =VLOOKUP(B4,Orders!A:B,2,FALSE) -> C0174
A5: OI000004 | B5: O00002 | C5: PR065 | D5: 1 | E5: 0.2 | F5: FALSE | G5: =VLOOKUP(C5,Products!A:D,4,FALSE) -> 2780 | H5: =VLOOKUP(C5,Products!A:D,3,FALSE) -> Apparel | I5: =G5*D5*(1-E5) -> 2224 | J5: =VLOOKUP(B5,Orders!A:C,3,FALSE) -> 45812 | K5: =VLOOKUP(B5,Orders!A:B,2,FALSE) -> C0174
A6: OI000005 | B6: O00003 | C6: PR068 | D6: 3 | E6: 0.05 | F6: FALSE | G6: =VLOOKUP(C6,Products!A:D,4,FALSE) -> 3000 | H6: =VLOOKUP(C6,Products!A:D,3,FALSE) -> Home & Kitchen | I6: =G6*D6*(1-E6) -> 8550 | J6: =VLOOKUP(B6,Orders!A:C,3,FALSE) -> 46105 | K6: =VLOOKUP(B6,Orders!A:B,2,FALSE) -> C0039
A7: OI000006 | B7: O00003 | C7: PR007 | D7: 2 | E7: 0 | F7: FALSE | G7: =VLOOKUP(C7,Products!A:D,4,FALSE) -> 5550 | H7: =VLOOKUP(C7,Products!A:D,3,FALSE) -> Home & Kitchen | I7: =G7*D7*(1-E7) -> 11100 | J7: =VLOOKUP(B7,Orders!A:C,3,FALSE) -> 46105 | K7: =VLOOKUP(B7,Orders!A:B,2,FALSE) -> C0039
A8: OI000007 | B8: O00004 | C8: PR044 | D8: 4 | E8: 0.1 | F8: FALSE | G8: =VLOOKUP(C8,Products!A:D,4,FALSE) -> 1440 | H8: =VLOOKUP(C8,Products!A:D,3,FALSE) -> Sports | I8: =G8*D8*(1-E8) -> 5184 | J8: =VLOOKUP(B8,Orders!A:C,3,FALSE) -> 46234 | K8: =VLOOKUP(B8,Orders!A:B,2,FALSE) -> C0204
A9: OI000008 | B9: O00004 | C9: PR059 | D9: 2 | E9: 0 | F9: FALSE | G9: =VLOOKUP(C9,Products!A:D,4,FALSE) -> 2200 | H9: =VLOOKUP(C9,Products!A:D,3,FALSE) -> Electronics | I9: =G9*D9*(1-E9) -> 4400 | J9: =VLOOKUP(B9,Orders!A:C,3,FALSE) -> 46234 | K9: =VLOOKUP(B9,Orders!A:B,2,FALSE) -> C0204
A10: OI000009 | B10: O00004 | C10: PR024 | D10: 1 | E10: 0.05 | F10: FALSE | G10: =VLOOKUP(C10,Products!A:D,4,FALSE) -> 99 | H10: =VLOOKUP(C10,Products!A:D,3,FALSE) -> Electronics | I10: =G10*D10*(1-E10) -> 94.05 | J10: =VLOOKUP(B10,Orders!A:C,3,FALSE) -> 46234 | K10: =VLOOKUP(B10,Orders!A:B,2,FALSE) -> C0204
A11: OI000010 | B11: O00004 | C11: PR043 | D11: 2 | E11: 0 | F11: FALSE | G11: =VLOOKUP(C11,Products!A:D,4,FALSE) -> 1660 | H11: =VLOOKUP(C11,Products!A:D,3,FALSE) -> Apparel | I11: =G11*D11*(1-E11) -> 3320 | J11: =VLOOKUP(B11,Orders!A:C,3,FALSE) -> 46234 | K11: =VLOOKUP(B11,Orders!A:B,2,FALSE) -> C0204
A12: OI000011 | B12: O00005 | C12: PR001 | D12: 4 | E12: 0 | F12: FALSE | G12: =VLOOKUP(C12,Products!A:D,4,FALSE) -> 2400 | H12: =VLOOKUP(C12,Products!A:D,3,FALSE) -> Electronics | I12: =G12*D12*(1-E12) -> 9600 | J12: =VLOOKUP(B12,Orders!A:C,3,FALSE) -> 46169 | K12: =VLOOKUP(B12,Orders!A:B,2,FALSE) -> C0188
A13: OI000012 | B13: O00005 | C13: PR027 | D13: 2 | E13: 0.1 | F13: FALSE | G13: =VLOOKUP(C13,Products!A:D,4,FALSE) -> 420 | H13: =VLOOKUP(C13,Products!A:D,3,FALSE) -> Beauty | I13: =G13*D13*(1-E13) -> 756 | J13: =VLOOKUP(B13,Orders!A:C,3,FALSE) -> 46169 | K13: =VLOOKUP(B13,Orders!A:B,2,FALSE) -> C0188
... A1556: OI001556 | B1556: O00899 | C1556: PR030 | D1556: 3 | E1556: 0.15 | F1556: FALSE | G1556: =VLOOKUP(C1556,Products!A:D,4,FALSE) -> 1440 | H1556: =VLOOKUP(C1556,Products!A:D,3,FALSE) -> Sports | I1556: =G1556*D1556*(1-E1556) -> 3672 | J1556: =VLOOKUP(B1556,Orders!A:C,3,FALSE) -> 45901 | K1556: =VLOOKUP(B1556,Orders!A:B,2,FALSE) -> C0216
A1557: OI001557 | B1557: O00900 | C1557: PR011 | D1557: 3 | E1557: 0.2 | F1557: FALSE
A1558: OI001558 | B1558: O00016 | C1558: PR070 | D1558: 1 | E1558: 0.2 | F1558: FALSE
A1559: OI001559 | B1559: O00016 | C1559: PR036 | D1559: 2 | E1559: 0 | F1559: FALSE | G1559: =VLOOKUP(C1559,Products!A:D,4,FALSE) -> 330 | H1559: =VLOOKUP(C1559,Products!A:D,3,FALSE) -> Books | I1559: =G1559*D1559*(1-E1559) -> 660 | J1559: =VLOOKUP(B1559,Orders!A:C,3,FALSE) -> 45900 | K1559: =VLOOKUP(B1559,Orders!A:B,2,FALSE) -> C0050

Sheet Orders
A1: order_id | B1: customer_id | C1: order_date | D1: status | E1: payment_method
A2: O00001 | B2: C0247 | C2: 46260 | D2: Returned | E2: Net Banking
A3: O00002 | B3: C0174 | C3: 45812 | D3: Cancelled | E3: COD
A4: O00003 | B4: C0039 | C4: 46105 | D4: Delivered | E4: UPI
A5: O00004 | B5: C0204 | C5: 46234 | D5: Returned | E5: Wallet
A6: O00005 | B6: C0188 | C6: 46169 | D6: Delivered | E6: COD
A7: O00006 | B7: C0008 | C7: 46133 | D7: Delivered | E7: Credit Card
A8: O00007 | B8: C0233 | C8: 45938 | D8: Delivered | E8: Net Banking
A9: O00008 | B9: C0300 | C9: 46254 | D9: Delivered | E9: Net Banking
A10: O00009 | B10: C0056 | C10: 46037 | D10: Shipped | E10: COD
A11: O00010 | B11: C0013 | C11: 46038 | D11: Shipped | E11: Wallet
A12: O00011 | B12: C0168 | C12: 45801 | D12: Cancelled | E12: UPI
A13: O00012 | B13: C0033 | C13: 45736 | D13: Shipped | E13: COD
... A900: O00900 | B900: C0191 | C900: 46275 | D900: Delivered | E900: Unknown

Sheet Products
A1: product_id | B1: product_name | C1: category | D1: unit_price | E1: unit_cost | F1: stock_qty | G1: price_was_imputed
A2: PR001 | B2: Radio Max | C2: Electronics | D2: 2400 | E2: 1170 | F2: 326 | G2: FALSE
A3: PR002 | B3: Technology Classic | C3: Beauty | D3: 1630 | E3: 1080 | F3: 145 | G3: FALSE
A4: PR003 | B4: Yard Max | C4: Beauty | D4: 2580 | E4: 1370 | F4: 494 | G4: FALSE
A5: PR004 | B5: Away Plus | C5: Electronics | D5: 3630 | E5: 2480 | F5: 58 | G5: FALSE
A6: PR005 | B6: Skin Classic | C6: Electronics | D6: 1520 | E6: 830 | F6: 322 | G6: FALSE
A7: PR006 | B7: Rich Classic | C7: Books | D7: 1520 | E7: 680 | F7: 485 | G7: FALSE
A8: PR007 | B8: Class Pro | C8: Home & Kitchen | D8: 5550 | E8: 38750 | F8: 285 | G8: FALSE
A9: PR008 | B9: Agent Plus | C9: Beauty | D9: 2720 | E9: 1720 | F9: 230 | G9: FALSE
A10: PR009 | B10: Machine Plus | C10: Beauty | D10: 1240 | E10: 820 | F10: 156 | G10: FALSE
A11: PR010 | B11: Series Pro | C11: Sports | D11: 2450 | E11: 1020 | F11: 485 | G11: FALSE
A12: PR011 | B12: Glass Pro | C12: Apparel | D12: 1240 | E12: 570 | F12: 80 | G12: FALSE
A13: PR012 | B13: Always Max | C13: Apparel | D13: 1240 | E13: 700 | F13: 1 | G13: FALSE
... A81: PR080 | B81: Find Lite | C81: Sports | D81: 99 | E81: 60 | F81: 467 | G81: FALSE

Sheet RFM
A1: customer_id | B1: recency | C1: frequency | D1: monetary | E1: R_score | F1: F_score | G1: M_score | H1: RFM_score | I1: segment
A2: C0001 | B2: 5 | C2: 1 | D2: 4020 | E2: 5 | F2: 1 | G2: 1 | H2: 511 | I2: New Customers
A3: C0002 | B3: 252 | C3: 2 | D3: 6898.45 | E3: 2 | F3: 1 | G3: 1 | H3: 211 | I3: Lost
A4: C0003 | B4: 509 | C4: 1 | D4: 6460 | E4: 1 | F4: 1 | G4: 1 | H4: 111 | I4: Lost
A5: C0004 | B5: 4 | C5: 5 | D5: 46941.3 | E5: 5 | F5: 5 | G5: 5 | H5: 555 | I5: Champions
A6: C0005 | B6: 83 | C6: 8 | D6: 59760 | E6: 4 | F6: 5 | G6: 5 | H6: 455 | I6: Champions
A7: C0006 | B7: 375 | C7: 2 | D7: 19265 | E7: 1 | F7: 1 | G7: 3 | H7: 113 | I7: Lost
A8: C0007 | B8: 384 | C8: 1 | D8: 3420 | E8: 1 | F8: 1 | G8: 1 | H8: 111 | I8: Lost
A9: C0008 | B9: 149 | C9: 1 | D9: 6964 | E9: 3 | F9: 1 | G9: 1 | H9: 311 | I9: Potential Loyalists
A10: C0009 | B10: 2 | C10: 8 | D10: 103834.3 | E10: 5 | F10: 5 | G10: 5 | H10: 555 | I10: Champions
A11: C0010 | B11: 434 | C11: 1 | D11: 10120 | E11: 1 | F11: 1 | G11: 1 | H11: 111 | I11: Lost
A12: C0011 | B12: 73 | C12: 2 | D12: 27557 | E12: 4 | F12: 2 | G12: 4 | H12: 424 | I12: New Customers
A13: C0012 | B13: 70 | C13: 2 | D13: 11724 | E13: 4 | F13: 2 | G13: 2 | H13: 422 | I13: New Customers
... A290: C0300 | B290: 28 | C290: 2 | D290: 8998 | E290: 5 | F290: 3 | G290: 1 | H290: 531 | I290: Potential Loyalists

Sheet Pivot_Category
A3: Row Labels | B3: Sum of line_total
A4: Apparel | B4: 1092678.5
A5: Beauty | B5: 1481006
A6: Books | B6: 978156.75
A7: Electronics | B7: 1367944.2
A8: Home & Kitchen | B8: 1693539.5
A9: Sports | B9: 1038613
A10: Grand Total | B10: 7651938

Sheet Pivot_TopCustomers
A3: Row Labels | B3: Sum of line_total
A4: C0009 | B4: 103834.3
A5: C0192 | B5: 93445.9
A6: C0053 | B6: 76791.5
A7: C0122 | B7: 76273.2
A8: C0263 | B8: 76140.4
A9: C0167 | B9: 70155.5
A10: C0185 | B10: 69856.5
A11: C0204 | B11: 68005.05
A12: C0052 | B12: 67353
A13: C0155 | B13: 66569
A14: Grand Total | B14: 768424.35

Sheet Pivot_RFM
A3: Row Labels | B3: Count of customer_id
A4: At Risk | B4: 23
A5: Champions | B5: 55
A6: Lost | B6: 72
A7: New Customers | B7: 30
A8: Potential Loyalists | B8: 109
A9: Grand Total | B9: 289

Sheet Pivot_MonthlyRevenue
A3: Row Labels | B3: Sum of line_total
A4: 2025
A5: Mar | B5: 203770.5
A6: Apr | B6: 416421
A7: May | B7: 402497.6
A8: Jun | B8: 454569.4
A9: Jul | B9: 467131
A10: Aug | B10: 579476.85
A11: Sep | B11: 411700.8
A12: Oct | B12: 517817.7
A13: Nov | B13: 296917.3
A14: Dec | B14: 568416.75
A15: 2026
A16: Jan | B16: 444987.15
A17: Feb | B17: 380897.5
A18: Mar | B18: 518985.55
A19: Apr | B19: 413045.1
A20: May | B20: 409956.8
A21: Jun | B21: 383199.9
A22: Jul | B22: 323977.3
A23: Aug | B23: 348412.1
A24: Sep | B24: 109757.7
A25: Grand Total | B25: 7651938

Sheet Summary
A1: E-commerce Sales & Customer Performance Summary
A6: Total Revenue: ₹76,51,938 | H6: Total Orders: 899 | O6: Delivered Rate: 56%
